waveanalysis/__init__.py
waveanalysis/__main__.py
waveanalysis/runner.py
waveanalysis/custom_gui/__init__.py
waveanalysis/custom_gui/custom_gui.py
waveanalysis/data_workflows/__init__.py
waveanalysis/data_workflows/combined_workflow.py
waveanalysis/data_workflows/rolling_workflow.py
waveanalysis/housekeeping/__init__.py
waveanalysis/housekeeping/housekeeping_functions.py
waveanalysis/image_props/__init__.py.py
waveanalysis/image_props/image_bin_calc.py
waveanalysis/image_props/image_properties.py
waveanalysis/image_props/image_to_np_arrays.py
waveanalysis/plotting/__init__.py
waveanalysis/plotting/group_plotting.py
waveanalysis/plotting/indv_plot_creation.py
waveanalysis/plotting/mean_plot_creation.py
waveanalysis/plotting/rolling_plot_creation.py
waveanalysis/signal_processing/__init__.py
waveanalysis/signal_processing/correlation_functions.py
waveanalysis/signal_processing/peak_properties.py
waveanalysis/summarize_save/__init__.py
waveanalysis/summarize_save/save_stats.py
waveanalysis/summarize_save/summarize_images.py
waveanalysis-0.1.0rc1.dist-info/METADATA
waveanalysis-0.1.0rc1.dist-info/WHEEL
waveanalysis-0.1.0rc1.dist-info/licenses/LICENSE
waveanalysis-0.1.0rc1.dist-info/RECORD
