Metadata-Version: 2.4
Name: waveanalysis
Version: 0.1.0rc1
Summary: imaging processing of oscillatory dynamics
Author-email: Zac Swider <zac.swider@gmail.com>, Dominic Chomchai <chomchai@wisc.edu>
License: GNU General Public License v3.0
License-File: LICENSE
Classifier: License :: OSI Approved :: GNU General Public License v3 (GPLv3)
Classifier: Programming Language :: Python :: 3
Classifier: Programming Language :: Python :: 3.9
Requires-Python: <3.10,>=3.9
Requires-Dist: matplotlib==3.7.1
Requires-Dist: numpy==1.25.0
Requires-Dist: pandas==1.5.3
Requires-Dist: scipy==1.10.1
Requires-Dist: seaborn==0.12.2
Requires-Dist: tifffile==2021.7.2
Requires-Dist: tqdm==4.65.0
